morphqs/__init__ 2.py
morphqs/__init__.py
morphqs/morphclass.py
morphqs/components/__init__.py
morphqs/components/ansible 2.py
morphqs/components/ansible.py
morphqs/components/integrations 2.py
morphqs/components/integrations.py
morphqs/components/uchigheredmsp 2.py
morphqs/components/uchigheredmsp 3.py
morphqs/components/uchigheredmsp.py
morphqs/components/usecasedeployment 2.py
morphqs/components/usecasedeployment.py
morphqs/logging/__init__.py
morphqs/logging/loghandler.py
morphqs-0.1.25.dist-info/LICENSE.txt
morphqs-0.1.25.dist-info/METADATA
morphqs-0.1.25.dist-info/WHEEL
morphqs-0.1.25.dist-info/top_level.txt
morphqs-0.1.25.dist-info/RECORD
