Metadata-Version: 2.1
Name: morphqs
Version: 0.1.25
Summary: Tool utilized to deploy some basic concepts for the Morpheus Data Platform
Home-page: https://gitlab.com/jaredlutgen/morphqs
Author: Jared Lutgen
Author-email: jlutgen@morpheusdata.com
License: MIT
Classifier: Development Status :: 4 - Beta
Classifier: License :: OSI Approved :: MIT License
Classifier: Programming Language :: Python
Classifier: Programming Language :: Python :: 3.5
Classifier: Programming Language :: Python :: 3.6
Classifier: Topic :: Software Development :: Libraries
Classifier: Topic :: Software Development :: Libraries :: Python Modules
Classifier: Intended Audience :: Developers
Requires-Python: >=3.5
License-File: LICENSE.txt
Requires-Dist: requests
